<metadata xml:lang="en"><Esri><CreaDate>20230214</CreaDate><CreaTime>12511500</CreaTime><ArcGISFormat>1.0</ArcGISFormat><SyncOnce>FALSE</SyncOnce><DataProperties><itemProps><itemName Sync="TRUE">SF_Velocity_2021.tif</itemName><imsContentType Sync="TRUE">002</imsContentType><nativeExtBox><westBL Sync="TRUE">376000.000000</westBL><eastBL Sync="TRUE">426000.000000</eastBL><southBL Sync="TRUE">5075000.000000</southBL><northBL Sync="TRUE">5105000.000000</northBL><exTypeCode Sync="TRUE">1</exTypeCode></nativeExtBox><itemLocation><linkage Sync="TRUE">file://C:\QGIS\UWW_HSI\SF_Velocity_2021.tif</linkage><protocol Sync="TRUE">Local Area Network</protocol></itemLocation></itemProps><coordRef><type Sync="TRUE">Projected</type><geogcsn Sync="TRUE">GCS_North_American_1983</geogcsn><csUnits Sync="TRUE">Linear Unit: Meter (1.000000)</csUnits><projcsn Sync="TRUE">NAD_1983_UTM_Zone_11N</projcsn><peXml Sync="TRUE">&lt;ProjectedCoordinateSystem xsi:type='typens:ProjectedCoordinateSystem' xmlns:xsi='http://www.w3.org/2001/XMLSchema-instance' xmlns:xs='http://www.w3.org/2001/XMLSchema' xmlns:typens='http://www.esri.com/schemas/ArcGIS/10.8'&gt;&lt;WKT&gt;PROJCS[&amp;quot;NAD_1983_UTM_Zone_11N&amp;quot;,GEOGCS[&amp;quot;GCS_North_American_1983&amp;quot;,DATUM[&amp;quot;D_North_American_1983&amp;quot;,SPHEROID[&amp;quot;GRS_1980&amp;quot;,6378137.0,298.257222101]],PRIMEM[&amp;quot;Greenwich&amp;quot;,0.0],UNIT[&amp;quot;Degree&amp;quot;,0.0174532925199433]],PROJECTION[&amp;quot;Transverse_Mercator&amp;quot;],PARAMETER[&amp;quot;False_Easting&amp;quot;,500000.0],PARAMETER[&amp;quot;False_Northing&amp;quot;,0.0],PARAMETER[&amp;quot;Central_Meridian&amp;quot;,-117.0],PARAMETER[&amp;quot;Scale_Factor&amp;quot;,0.9996],PARAMETER[&amp;quot;Latitude_Of_Origin&amp;quot;,0.0],UNIT[&amp;quot;Meter&amp;quot;,1.0],AUTHORITY[&amp;quot;EPSG&amp;quot;,26911]]&lt;/WKT&gt;&lt;XOrigin&gt;-5120900&lt;/XOrigin&gt;&lt;YOrigin&gt;-9998100&lt;/YOrigin&gt;&lt;XYScale&gt;450445547.3910538&lt;/XYScale&gt;&lt;ZOrigin&gt;-100000&lt;/ZOrigin&gt;&lt;ZScale&gt;10000&lt;/ZScale&gt;&lt;MOrigin&gt;-100000&lt;/MOrigin&gt;&lt;MScale&gt;10000&lt;/MScale&gt;&lt;XYTolerance&gt;0.001&lt;/XYTolerance&gt;&lt;ZTolerance&gt;0.001&lt;/ZTolerance&gt;&lt;MTolerance&gt;0.001&lt;/MTolerance&gt;&lt;HighPrecision&gt;true&lt;/HighPrecision&gt;&lt;WKID&gt;26911&lt;/WKID&gt;&lt;LatestWKID&gt;26911&lt;/LatestWKID&gt;&lt;/ProjectedCoordinateSystem&gt;</peXml></coordRef><lineage><Process ToolSource="c:\program files\arcgis\pro\Resources\ArcToolbox\toolboxes\Data Management Tools.tbx\CopyRaster" Date="20230214" Time="125118" Name="" export="">CopyRaster "Velocity (02NOV2022 06 00 00).2021LiDAR_be.2021LiDAR_be.tif" R:\Projects\Walla_Walla_HUC53\UpperWW_Watershed_Assessment\GIS\Data\Deliverable_data\To_Sharepoint\NF_SF_20230214.gdb\Velocity__02NOV2022_06_00_00__2021LiDAR_be_2021LiDAR_be_tif # # -9999 NONE NONE # NONE NONE "Esri Grid format" NONE CURRENT_SLICE NO_TRANSPOSE</Process><Process ToolSource="c:\program files\arcgis\pro\Resources\ArcToolbox\toolboxes\Data Management Tools.tbx\Rename" Date="20230214" Time="125336" Name="" export="">Rename R:\Projects\Walla_Walla_HUC53\UpperWW_Watershed_Assessment\GIS\Data\Deliverable_data\To_Sharepoint\NF_SF_20230214.gdb\Velocity__02NOV2022_06_00_00__2021LiDAR_be_2021LiDAR_be_tif R:\Projects\Walla_Walla_HUC53\UpperWW_Watershed_Assessment\GIS\Data\Deliverable_data\To_Sharepoint\NF_SF_20230214.gdb\SF_Velocity_PostFlood_LowFlow RasterDataset</Process><Process ToolSource="c:\program files\arcgis\pro\Resources\ArcToolbox\toolboxes\Data Management Tools.tbx\Rename" Date="20230214" Time="125451" Name="" export="">Rename R:\Projects\Walla_Walla_HUC53\UpperWW_Watershed_Assessment\GIS\Data\Deliverable_data\To_Sharepoint\NF_SF_20230214.gdb\SF_Velocity_PostFlood_LowFlow R:\Projects\Walla_Walla_HUC53\UpperWW_Watershed_Assessment\GIS\Data\Deliverable_data\To_Sharepoint\NF_SF_20230214.gdb\SF_Velocity_2021lidar_LowFlow RasterDataset</Process><Process ToolSource="c:\program files\arcgis\pro\Resources\ArcToolbox\toolboxes\Data Management Tools.tbx\Rename" Date="20230214" Time="130607" Name="" export="">Rename R:\Projects\Walla_Walla_HUC53\UpperWW_Watershed_Assessment\GIS\Data\Deliverable_data\To_Sharepoint\NF_SF_20230214.gdb\SF_Velocity_2021lidar_LowFlow R:\Projects\Walla_Walla_HUC53\UpperWW_Watershed_Assessment\GIS\Data\Deliverable_data\To_Sharepoint\NF_SF_20230214.gdb\SF_Velocity_metric_2021lidar_LowFlow RasterDataset</Process><Process ToolSource="c:\program files (x86)\arcgis\desktop10.8\ArcToolbox\Toolboxes\Data Management Tools.tbx\CopyRaster" Date="20230215" Time="133210">CopyRaster C:\QGIS\NF_SF_20230214.gdb\SF_Velocity_metric_2021lidar_LowFlow C:\QGIS\UWW_HSI\SF_Velocity_2021.tif # # -3.402823e+38 NONE NONE # NONE NONE TIFF NONE</Process></lineage><RasterProperties><General><PixelDepth Sync="TRUE">32</PixelDepth><HasColormap Sync="TRUE">FALSE</HasColormap><CompressionType Sync="TRUE">LZW</CompressionType><NumBands Sync="TRUE">1</NumBands><Format Sync="TRUE">TIFF</Format><HasPyramids Sync="TRUE">TRUE</HasPyramids><SourceType Sync="TRUE">continuous</SourceType><PixelType Sync="TRUE">floating point</PixelType><NoDataValue Sync="TRUE">-3.4028231e+38</NoDataValue></General></RasterProperties></DataProperties><SyncDate>20230215</SyncDate><SyncTime>13320800</SyncTime><ModDate>20230215</ModDate><ModTime>13320800</ModTime><scaleRange><minScale>150000000</minScale><maxScale>5000</maxScale></scaleRange><ArcGISProfile>ItemDescription</ArcGISProfile></Esri><dataIdInfo><envirDesc Sync="TRUE"> Version 6.2 (Build 9200) ; Esri ArcGIS 10.9.1.28388</envirDesc><dataLang><languageCode value="eng" Sync="TRUE"/><countryCode value="USA" Sync="TRUE"/></dataLang><idCitation><resTitle Sync="TRUE">SF_Velocity_2021.tif</resTitle><presForm><PresFormCd value="005" Sync="TRUE"/></presForm></idCitation><spatRpType><SpatRepTypCd value="002" Sync="TRUE"/></spatRpType><dataExt><geoEle xmlns=""><GeoBndBox esriExtentType="search"><exTypeCode Sync="TRUE">1</exTypeCode><westBL Sync="TRUE">-118.603931</westBL><eastBL Sync="TRUE">-117.952669</eastBL><northBL Sync="TRUE">46.094567</northBL><southBL Sync="TRUE">45.817414</southBL></GeoBndBox></geoEle></dataExt><idPurp>Created by: Rio ASE 2023

Created for: CTUIR

Purpose: Upper Walla Walla Watershed Assessment. Model is considered coarse-scale for planning/assessment level purposes.

HECRAS version: 6.3.1

Coordinate system and units: NAD 83 UTM Zone 11 N, system international (metric) units

Outputs: Hydraulic result rasters were created at a variety of flows (described below). Outputs are in metric units (meters for depth, etc.) 

Raster naming convention: Tributary (North Fork (NF), South Fork (SF), and mainstem Walla Walla (WW))_Hydraulic Metric (depth, velocity, or shear stress)_metric/imperial_elevationdata (2019/pre-flood or 2021/post-flood)_flowused (refers to recurrence interval of flow (e.g. 2-yr) or low flow (see below))

Terrain: 
-2021 Post-flood terrain: 2021 LiDAR (1 meter by 1 meter DEM) provided by CTUIR, supplemented with 2016 LiDAR (in Oregon) and 2018 LiDAR (in Washington) in some portions of floodplain within the model domain.
-2019 Pre-flood terrain: 2019 LiDAR (1 meter by 1 meter DEM) provided by CTUIR, supplemented with 2016 LiDAR (in Oregon) and 2018 LiDAR (in Washington) in some portions of floodplain within the model domain.
Manning’s n: Digitized using terrain data and aerial photography as reference (ortho_1-1hn_s_wa071_2019_1.sid, ortho1-1_hs_s_or059_2017_1.sid, and Walla_Walla_RGBI.sid provided by CTUIR). Manning's n layer considered coarse scale. 

Hydrology: Most of flows modeled are representative of discharges at a given recurrence interval (included in the raster name). These flows were calculated for various gages (USGS, WWBWC, and WDOE) within the watershed, and were then interpolated or extrapolated using drainage area as the independent variable. Low flow was calculated in a similar manner, but is associated with the daily average 95% exceedance flow in the summer (from July through September). See Upper Walla Walla River Watershed Assessment and Action Plan (2023) for a detailed description of approach and methods.
</idPurp><searchKeys><keyword>CTUIR</keyword><keyword>hydraulic modeling</keyword><keyword>Rio ASE</keyword></searchKeys></dataIdInfo><mdLang><languageCode value="eng" Sync="TRUE"/><countryCode value="USA" Sync="TRUE"/></mdLang><distInfo><distFormat><formatName Sync="TRUE">Raster Dataset</formatName></distFormat></distInfo><mdHrLv><ScopeCd value="005" Sync="TRUE"/></mdHrLv><mdHrLvName Sync="TRUE">dataset</mdHrLvName><refSysInfo><RefSystem><refSysID><identCode code="26911" Sync="TRUE"/><idCodeSpace Sync="TRUE">EPSG</idCodeSpace><idVersion Sync="TRUE">6.11(3.0.1)</idVersion></refSysID></RefSystem></refSysInfo><spdoinfo><rastinfo><rasttype Sync="TRUE">Pixel</rasttype><rowcount Sync="TRUE">30000</rowcount><colcount Sync="TRUE">50000</colcount><rastxsz Sync="TRUE">1.000000</rastxsz><rastysz Sync="TRUE">1.000000</rastysz><rastbpp Sync="TRUE">32</rastbpp><vrtcount Sync="TRUE">1</vrtcount><rastorig Sync="TRUE">Upper Left</rastorig><rastcmap Sync="TRUE">FALSE</rastcmap><rastcomp Sync="TRUE">LZ77</rastcomp><rastband Sync="TRUE">1</rastband><rastdtyp Sync="TRUE">pixel codes</rastdtyp><rastifor Sync="TRUE">FGDBR</rastifor><rastplyr Sync="TRUE">TRUE</rastplyr></rastinfo></spdoinfo><spref><horizsys><planar><planci><plance Sync="TRUE">row and column</plance><coordrep><absres Sync="TRUE">1.000000</absres><ordres Sync="TRUE">1.000000</ordres></coordrep></planci></planar></horizsys></spref><mdDateSt Sync="TRUE">20230215</mdDateSt><spatRepInfo><Georect><cellGeo><CellGeoCd Sync="TRUE" value="002"></CellGeoCd></cellGeo><numDims Sync="TRUE">2</numDims><tranParaAv Sync="TRUE">1</tranParaAv><chkPtAv Sync="TRUE">0</chkPtAv><cornerPts><pos Sync="TRUE">376000.000000 5075000.000000</pos></cornerPts><cornerPts><pos Sync="TRUE">376000.000000 5105000.000000</pos></cornerPts><cornerPts><pos Sync="TRUE">426000.000000 5105000.000000</pos></cornerPts><cornerPts><pos Sync="TRUE">426000.000000 5075000.000000</pos></cornerPts><centerPt><pos Sync="TRUE">401000.000000 5090000.000000</pos></centerPt><axisDimension type="002"><dimSize Sync="TRUE">50000</dimSize><dimResol><value Sync="TRUE" uom="m">1.000000</value></dimResol></axisDimension><axisDimension type="001"><dimSize Sync="TRUE">30000</dimSize><dimResol><value Sync="TRUE" uom="m">1.000000</value></dimResol></axisDimension><ptInPixel><PixOrientCd Sync="TRUE" value="001"></PixOrientCd></ptInPixel></Georect></spatRepInfo><contInfo><ImgDesc><contentTyp><ContentTypCd Sync="TRUE" value="001"></ContentTypCd></contentTyp><covDim><Band><dimDescrp Sync="TRUE">Band_1</dimDescrp><maxVal Sync="TRUE">1.903335</maxVal><minVal Sync="TRUE">0.000000</minVal><bitsPerVal Sync="TRUE">32</bitsPerVal><valUnit><UOM type="length"></UOM></valUnit></Band></covDim></ImgDesc></contInfo></metadata>
